xnatpytools/__init__.py
xnatpytools/utils.py
xnatpytools/bulksharing/__init__.py
xnatpytools/bulksharing/bulksharing.py
xnatpytools-0.7.0.dist-info/LICENSE
xnatpytools-0.7.0.dist-info/METADATA
xnatpytools-0.7.0.dist-info/WHEEL
xnatpytools-0.7.0.dist-info/entry_points.txt
xnatpytools-0.7.0.dist-info/top_level.txt
xnatpytools-0.7.0.dist-info/RECORD
