Metadata-Version: 2.1
Name: xnatpytools
Version: 0.7.0
Summary: Collection of Python tools for working with XNAT
Home-page: https://github.com/rbrecheisen/xnatpytools
Author: Ralph Brecheisen
Author-email: r.brecheisen@maastrichtuniversity.nl
License: MIT license
Keywords: xnatpytools
Platform: UNKNOWN
Classifier: Development Status :: 2 - Pre-Alpha
Classifier: Intended Audience :: Developers
Classifier: License :: OSI Approved :: MIT License
Classifier: Natural Language :: English
Classifier: Programming Language :: Python :: 3
Classifier: Programming Language :: Python :: 3.5
Classifier: Programming Language :: Python :: 3.6
Classifier: Programming Language :: Python :: 3.7
Classifier: Programming Language :: Python :: 3.8
Requires-Python: >=3.5
License-File: LICENSE
Requires-Dist: xnat
